islamic_times/time_equations.py
islamic_times/islamic_times.py
islamic_times/moon_equations.py
islamic_times/_version.py
islamic_times/astro_core.cpython-312-darwin.so
islamic_times/it_dataclasses.py
islamic_times/calculation_equations.py
islamic_times/__init__.py
islamic_times/prayer_times.py
islamic_times/sun_equations.py
islamic_times-2.1.0.dist-info/RECORD
islamic_times-2.1.0.dist-info/WHEEL
islamic_times-2.1.0.dist-info/top_level.txt
islamic_times-2.1.0.dist-info/METADATA
