Metadata-Version: 2.4
Name: islamic_times
Version: 2.1.0
Summary: Various calculations for Islamic purposes
Home-page: https://github.com/hassantahan/islamic_times
Author: Hassan Tahan
Author-email: contact@hassantahan.com
License: MIT
Classifier: Development Status :: 3 - Alpha
Classifier: Intended Audience :: Developers
Classifier: License :: OSI Approved :: MIT License
Classifier: Programming Language :: Python :: 3.10
Classifier: Programming Language :: Python :: 3.11
Classifier: Programming Language :: Python :: 3.12
Classifier: Programming Language :: Python :: 3.13
Requires-Python: >=3.10
Requires-Dist: numpy
Requires-Dist: timezonefinder
Requires-Dist: pytz
Requires-Dist: matplotlib
Requires-Dist: shapely
Requires-Dist: geopandas
Dynamic: author
Dynamic: author-email
Dynamic: classifier
Dynamic: description
Dynamic: description-content-type
Dynamic: home-page
Dynamic: license
Dynamic: requires-dist
Dynamic: requires-python
Dynamic: summary
